pycdhit/__init__.py
pycdhit/_class.py
pycdhit/_commands.py
pycdhit/_io.py
py_cdhit-1.1.5.dist-info/METADATA
py_cdhit-1.1.5.dist-info/WHEEL
py_cdhit-1.1.5.dist-info/licenses/LICENSE
py_cdhit-1.1.5.dist-info/RECORD
