Metadata-Version: 2.4
Name: py-cdhit
Version: 1.1.5
Summary: A Python interface for CD-HIT package.
Project-URL: Homepage, https://yuanx749.github.io/py-cdhit/
Project-URL: Documentation, https://yuanx749.github.io/py-cdhit/
Project-URL: Repository, https://github.com/yuanx749/py-cdhit
Author-email: Xiao Yuan <yuanx749@gmail.com>
License-Expression: GPL-2.0-only
License-File: LICENSE
Keywords: bioinformatics,sequence-analysis
Classifier: Intended Audience :: Developers
Classifier: Intended Audience :: Science/Research
Classifier: Operating System :: POSIX :: Linux
Classifier: Programming Language :: Python :: 3
Classifier: Topic :: Scientific/Engineering :: Bio-Informatics
Requires-Python: >=3.8
Requires-Dist: pandas
Provides-Extra: dev
Requires-Dist: notebook>=6.5.4; extra == 'dev'
Requires-Dist: pre-commit==3.3.2; extra == 'dev'
Requires-Dist: pytest-cov>=4.0.0; extra == 'dev'
Requires-Dist: pytest>=7.0.0; extra == 'dev'
Requires-Dist: ruff==0.6.9; extra == 'dev'
